src/__init__.py
src/command_executor.py
src/config.py
src/container.py
src/exceptions.py
src/protocols.py
src/repository_context.py
src/server.py
src/tool_generator.py
src/yaml_loader.py
src/definitions/__init__.py
src/definitions/radicle-1.1.0.yaml
src/definitions/radicle-1.2.0.yaml
src/definitions/radicle-1.3.0.yaml
src/definitions/radicle-1.4.0.yaml
src/definitions/radicle-1.5.0.yaml
src/definitions/schema.py
src/definitions/schema_fixed.py
radicle_mcp_server-0.1.6.dist-info/METADATA
radicle_mcp_server-0.1.6.dist-info/WHEEL
radicle_mcp_server-0.1.6.dist-info/entry_points.txt
radicle_mcp_server-0.1.6.dist-info/licenses/LICENSE
radicle_mcp_server-0.1.6.dist-info/RECORD
