Metadata-Version: 2.4
Name: radicle-mcp-server
Version: 0.1.6
Summary: A Model Context Protocol (MCP) server for Radicle CLI with versioning support
Author: Empiria Ltd
License-Expression: MIT
License-File: LICENSE
Keywords: cli,decentralized,mcp,model-context-protocol,radicle,version-control
Classifier: Development Status :: 4 - Beta
Classifier: Intended Audience :: Developers
Classifier: License :: OSI Approved :: MIT License
Classifier: Programming Language :: Python :: 3
Classifier: Programming Language :: Python :: 3.13
Classifier: Programming Language :: Python :: 3.14
Classifier: Topic :: Software Development :: Version Control
Classifier: Topic :: System :: Systems Administration
Requires-Python: >=3.13
Requires-Dist: attrs>=25.4.0
Requires-Dist: fastmcp>=0.11.0
Requires-Dist: mcp>=1.22.0
Requires-Dist: pyyaml>=6.0.3
Requires-Dist: typer>=0.20.0
Provides-Extra: dev
Requires-Dist: pytest>=8.0.0; extra == 'dev'
